{
  "decks": [
    {
      "id": 1,
      "name": "Rendering in React",
      "description": "React's component structure allows for quickly building a complex web application that relies on DOM manipulation. "
    },
    {
      "name": "React Router",
      "description": "React Router is a collection of navigational components that compose declaratively with your application.",
      "id": 2
    },
    {
      "name": "A new deck and stuff",
      "description": "Trying a new deck",
      "id": 0.36530432183842665
    },
    {
      "name": "Here is a name!!!",
      "description": "A real description of what the deck does. ",
      "id": 0.20212932003006445
    }
  ],
  "cards": [
    {
      "id": 1,
      "front": "Differentiate between Real DOM and Virtual DOM.",
      "back": "Virtual DOM updates are faster but do not directly update the HTML",
      "deckId": 1
    },
    {
      "id": 2,
      "front": "How do you modify the state of a different React component?",
      "back": "Not at all! State is visible to the component only.",
      "deckId": 1
    },
    {
      "id": 3,
      "front": "How do you pass data 'down' to a React child component?",
      "back": "As properties or props",
      "deckId": 1
    },
    {
      "front": "What path will match the follow Route?\n<Route>\n  <NotFound />\n</Route>",
      "back": "All paths. A route with no path matches all URL's",
      "deckId": 2,
      "id": 4
    },
    {
      "front": "What does <Switch> do?",
      "back": "Renders the first matching child <Route> ",
      "deckId": 2,
      "id": 5
    },
    {
      "cards": [],
      "front": "b",
      "back": "b",
      "deckId": 1,
      "id": 7
    },
    {
      "front": "Why did the chicken cross the road?",
      "back": "To get to the other side!",
      "deckId": 1,
      "id": "_h544hio"
    },
    {
      "front": "Here is the first card in the deck.",
      "back": "This should be some sort of question.",
      "deckId": null,
      "id": "_5ppu0iy"
    },
    {
      "front": "Did this work?",
      "back": "It should have...",
      "deckId": null,
      "id": "_t0g2emt"
    },
    {
      "front": "One more time",
      "back": "Public speaking",
      "deckId": null,
      "id": "_hnz54t7"
    },
    {
      "front": "Front",
      "back": "back",
      "deckId": null,
      "id": "_8i97pf8"
    },
    {
      "front": "This works",
      "back": "And so does this",
      "deckId": 1,
      "id": "_axkllhg"
    },
    {
      "front": "Why is a raven like a writing desk? ",
      "back": "Here is a new card!",
      "id": "_cw07yfb",
      "deckId": 20212932003006444
    },
    {
      "front": "What is the DOM and stuff?",
      "back": "The DOM is a object that is a representation of the HTML page.",
      "id": "_dc5vjj3"
    },
    {
      "front": "Why is a raven like a writing desk?",
      "back": "Here is a third card. ",
      "id": "_rtcuf3h"
    },
    {
      "front": "Frist",
      "back": "Here is the back of the card.",
      "id": "_0idnzac",
      "deckId": "0.20212932003006445"
    },
    {
      "front": "Why is a raven like a writing desk? ",
      "back": "Because it can produce a few notes, though they are very flat; and it is never put with the wrong end in front!",
      "id": "_4xjk2m9",
      "deckId": 0.20212932003006445
    }
  ]
}